cwmscli/__init__.py
cwmscli/__main__.py
cwmscli/callbacks/__init__.py
cwmscli/commands/blob.py
cwmscli/commands/commands_cwms.py
cwmscli/commands/csv2cwms/.gitignore
cwmscli/commands/csv2cwms/README.md
cwmscli/commands/csv2cwms/__init__.py
cwmscli/commands/csv2cwms/__main__.py
cwmscli/commands/csv2cwms/examples/complete_config.json
cwmscli/commands/csv2cwms/examples/hourly.json
cwmscli/commands/csv2cwms/examples/minutes.json
cwmscli/commands/csv2cwms/tests/__init__.py
cwmscli/commands/csv2cwms/tests/data/.gitignore
cwmscli/commands/csv2cwms/tests/data/expected_brok_output.json
cwmscli/commands/csv2cwms/tests/data/sample_brok.csv
cwmscli/commands/csv2cwms/tests/data/sample_config.json
cwmscli/commands/csv2cwms/tests/skip_test_integration_pipeline.py
cwmscli/commands/csv2cwms/tests/test_dateutils.py
cwmscli/commands/csv2cwms/tests/test_expressions.py
cwmscli/commands/csv2cwms/tests/test_fileio.py
cwmscli/commands/csv2cwms/utils/__init__.py
cwmscli/commands/csv2cwms/utils/dateutils.py
cwmscli/commands/csv2cwms/utils/expression.py
cwmscli/commands/csv2cwms/utils/fileio.py
cwmscli/commands/csv2cwms/utils/logging.py
cwmscli/commands/csv2cwms/utils/terminal.py
cwmscli/commands/shef_critfile_import.py
cwmscli/requirements.py
cwmscli/usgs/__init__.py
cwmscli/usgs/getUSGS_ratings_cda.py
cwmscli/usgs/getusgs_cda.py
cwmscli/usgs/getusgs_measurements_cda.py
cwmscli/usgs/rating_ini_file_import.py
cwmscli/utils/__init__.py
cwmscli/utils/deps.py
cwms_cli-0.1.1.dist-info/METADATA
cwms_cli-0.1.1.dist-info/WHEEL
cwms_cli-0.1.1.dist-info/entry_points.txt
cwms_cli-0.1.1.dist-info/licenses/LICENSE
cwms_cli-0.1.1.dist-info/RECORD
